LICENSE
MANIFEST.in
README.md
setup.cfg
setup.py
lifoid_rasanlu/__init__.py
lifoid_rasanlu/config.py
lifoid_rasanlu/parser.py
lifoid_rasanlu.egg-info/PKG-INFO
lifoid_rasanlu.egg-info/SOURCES.txt
lifoid_rasanlu.egg-info/dependency_links.txt
lifoid_rasanlu.egg-info/requires.txt
lifoid_rasanlu.egg-info/top_level.txt
tests/__init__.py
tests/tests.py