Metadata-Version: 1.1
Name: lifoid-rasanlu
Version: 0.1.1
Summary: rasa_nlu plugin for Lifoid
Home-page: https://github.com/romaryd/lifoid-rasanlu
Author: Romary Dupuis
Author-email: romary@me.com
License:                                  Apache License
